{
  "main": {
    "id": "f18d0e7dc7348e7c",
    "type": "split",
    "children": [
      {
        "id": "5b89f3a1f5d4aef8",
        "type": "tabs",
        "children": [
          {
            "id": "310302acc5581560",
            "type": "leaf",
            "state": {
              "type": "markdown",
              "state": {
                "file": "day 2-linux.md",
                "mode": "source",
                "source": false
              }
            }
          }
        ]
      }
    ],
    "direction": "vertical"
  },
  "left": {
    "id": "6d5ad86e9391d50d",
    "type": "split",
    "children": [
      {
        "id": "f0e0359f6fc11bb5",
        "type": "tabs",
        "children": [
          {
            "id": "fcfddc42cc9f0ba3",
            "type": "leaf",
            "state": {
              "type": "file-explorer",
              "state": {
                "sortOrder": "alphabetical"
              }
            }
          },
          {
            "id": "e3c0b8e7f69c0de9",
            "type": "leaf",
            "state": {
              "type": "search",
              "state": {
                "query": " ",
                "matchingCase": false,
                "explainSearch": false,
                "collapseAll": false,
                "extraContext": false,
                "sortOrder": "alphabetical"
              }
            }
          },
          {
            "id": "d3686e425234e7c5",
            "type": "leaf",
            "state": {
              "type": "bookmarks",
              "state": {}
            }
          }
        ],
        "currentTab": 1
      }
    ],
    "direction": "horizontal",
    "width": 300
  },
  "right": {
    "id": "9a0d4056dedf62e1",
    "type": "split",
    "children": [
      {
        "id": "1f4b9084bbc29b20",
        "type": "tabs",
        "children": [
          {
            "id": "003c2c766f3e608f",
            "type": "leaf",
            "state": {
              "type": "backlink",
              "state": {
                "file": "day 2-linux.md",
                "collapseAll": false,
                "extraContext": false,
                "sortOrder": "alphabetical",
                "showSearch": false,
                "searchQuery": "",
                "backlinkCollapsed": false,
                "unlinkedCollapsed": true
              }
            }
          },
          {
            "id": "50b0c10caac0bc22",
            "type": "leaf",
            "state": {
              "type": "outgoing-link",
              "state": {
                "file": "day 2-linux.md",
                "linksCollapsed": false,
                "unlinkedCollapsed": true
              }
            }
          },
          {
            "id": "b60db0ded8d90b68",
            "type": "leaf",
            "state": {
              "type": "tag",
              "state": {
                "sortOrder": "frequency",
                "useHierarchy": true
              }
            }
          },
          {
            "id": "5024858404eb3dd7",
            "type": "leaf",
            "state": {
              "type": "outline",
              "state": {
                "file": "day 2-linux.md"
              }
            }
          }
        ]
      }
    ],
    "direction": "horizontal",
    "width": 300,
    "collapsed": true
  },
  "left-ribbon": {
    "hiddenItems": {
      "switcher:Open quick switcher": false,
      "graph:Open graph view": false,
      "canvas:Create new canvas": false,
      "daily-notes:Open today's daily note": false,
      "templates:Insert template": false,
      "command-palette:Open command palette": false
    }
  },
  "active": "310302acc5581560",
  "lastOpenFiles": [
    "DAY 1  Ethical hacking.md",
    "day 2-linux.md",
    "README.md",
    "Untitled.md"
  ]
}